croterline-1.0.10.dist-info/METADATA
croterline-1.0.10.dist-info/WHEEL
croterline-1.0.10.dist-info/entry_points.txt
croterline/__init__.py
croterline/context.py
croterline/process.py
croterline/py.typed
croterline/utils.py
croterline-1.0.10.dist-info/RECORD
