Metadata-Version: 2.1
Name: croterline
Version: 1.0.10
Summary: Default template for PDM package
Author-Email: snowykami <snowykami@outlook.com>
License: MIT
Requires-Python: >=3.10
Requires-Dist: magicoca>=1.0.6
